tmail/__init__.py
tmail/tmail.py
tmail/utils/__init__.py
tmail/utils/errors.py
tmail/utils/tools.py
xqctmail-0.0.3.dist-info/entry_points.txt
xqctmail-0.0.3.dist-info/LICENSE
xqctmail-0.0.3.dist-info/METADATA
xqctmail-0.0.3.dist-info/WHEEL
xqctmail-0.0.3.dist-info/RECORD
