Metadata-Version: 2.3
Name: XQCTmail
Version: 0.0.3
Summary: 一个基于 Python 的自动化临时邮箱工具，支持自动获取、切换、监听临时邮箱的新邮件，适合验证码接收、自动化测试等场景，支持循环监听新邮件。
Author: Xiaoqiang
Author-email: xiaoqiangclub@hotmail.com
Requires-Python: >=3.10
Classifier: Programming Language :: Python :: 3
Classifier: Programming Language :: Python :: 3.10
Classifier: Programming Language :: Python :: 3.11
Classifier: Programming Language :: Python :: 3.12
Classifier: Programming Language :: Python :: 3.13
Requires-Dist: autochrome (>=0.1.6)
Requires-Dist: loguru (>=0.7.2)
